{
  "annotations": {
    "list": [
      {
        "builtIn": 1,
        "datasource": "-- Grafana --",
        "enable": true,
        "hide": true,
        "iconColor": "rgba(0, 211, 255, 1)",
        "name": "Annotations & Alerts",
        "type": "dashboard"
      }
    ]
  },
  "editable": true,
  "gnetId": null,
  "graphTooltip": 0,
  "id": null,
  "links": [],
  "panels": [
    {
      "datasource": "Loki",
      "fieldConfig": {
        "defaults": {
          "color": {
            "mode": "palette-classic"
          },
          "custom": {
            "axisLabel": "",
            "axisPlacement": "auto",
            "barAlignment": 0,
            "drawStyle": "bars",
            "fillOpacity": 100,
            "gradientMode": "none",
            "hideFrom": {
              "tooltip": false,
              "viz": false,
              "legend": false
            },
            "lineInterpolation": "linear",
            "lineWidth": 1,
            "pointSize": 5,
            "scaleDistribution": {
              "type": "linear"
            },
            "showPoints": "never",
            "spanNulls": false,
            "stacking": {
              "group": "A",
              "mode": "normal"
            },
            "thresholdsStyle": {
              "mode": "off"
            }
          },
          "mappings": [],
          "thresholds": {
            "mode": "absolute",
            "steps": [
              {
                "color": "green",
                "value": null
              }
            ]
          },
          "unit": "short"
        },
        "overrides": []
      },
      "gridPos": {
        "h": 8,
        "w": 24,
        "x": 0,
        "y": 0
      },
      "id": 2,
      "options": {
        "legend": {
          "calcs": [],
          "displayMode": "list",
          "placement": "bottom"
        },
        "tooltip": {
          "mode": "single"
        }
      },
      "pluginVersion": "8.0.0",
      "targets": [
        {
          "expr": "sum(count_over_time({job=\"jobsphere-app\"} |= \"error\" [1m]))",
          "refId": "A",
          "legendFormat": "Errors"
        },
        {
          "expr": "sum(count_over_time({job=\"jobsphere-app\"} |= \"warn\" [1m]))",
          "refId": "B",
          "legendFormat": "Warnings"
        }
      ],
      "title": "Log Levels Over Time",
      "type": "timeseries"
    },
    {
      "datasource": "Loki",
      "gridPos": {
        "h": 12,
        "w": 24,
        "x": 0,
        "y": 8
      },
      "id": 4,
      "options": {
        "showLabels": false,
        "showTime": true,
        "sortOrder": "Descending",
        "wrapLogMessage": true,
        "enableLogDetails": true,
        "dedupStrategy": "none"
      },
      "targets": [
        {
          "expr": "{job=\"jobsphere-app\"}",
          "refId": "A"
        }
      ],
      "title": "Application Logs",
      "type": "logs"
    }
  ],
  "schemaVersion": 27,
  "style": "dark",
  "tags": ["jobsphere", "logs"],
  "templating": {
    "list": []
  },
  "time": {
    "from": "now-6h",
    "to": "now"
  },
  "timepicker": {},
  "timezone": "",
  "title": "JobSphere Application Logs",
  "uid": "jobsphere-logs",
  "version": 0
}
